{"iso_code":"BHR","generated_at":"2026-06-02T15:37:04-03:00","gas":"co2e_100yr","sectors":["power","fossil-fuel-operations","manufacturing","mineral-extraction"],"assets":[{"id":452755,"name":"Aluminium Bahrain (ALBA) power station","sector":"electricity-generation","type":"gas, other_fossil","lon":50.5951,"lat":26.0911,"emissions":8722700.0},{"id":53058555,"name":"Bahrain_Widyan - North Arabian Gulf_Conventional onshore","sector":"oil-and-gas-production","type":"","lon":50.55794,"lat":26.03463,"emissions":7092511.6},{"id":453012,"name":"Al-Dur Power and Water Station","sector":"electricity-generation","type":"gas, other_fossil","lon":50.608,"lat":25.9693,"emissions":6524600.0},{"id":3143738,"name":"Bahrain Petroleum Company Refinery","sector":"oil-and-gas-refining","type":"Deep Conversion","lon":50.6046,"lat":26.11657,"emissions":4006005.5},{"id":25451381,"name":"Riffa Power and Water Station","sector":"electricity-generation","type":"gas","lon":50.5895,"lat":26.1203,"emissions":3552200.0},{"id":3672952,"name":"Askar aluminium plant","sector":"aluminum","type":"Smelting","lon":50.60294,"lat":26.08781,"emissions":3506477.9},{"id":448579,"name":"Al Hidd Power and Water Station","sector":"electricity-generation","type":"gas, other_fossil","lon":50.6621,"lat":26.2223,"emissions":2508500.0},{"id":450570,"name":"Al Ezzel power station","sector":"electricity-generation","type":"gas, other_fossil","lon":50.6595,"lat":26.2175,"emissions":2174900.0},{"id":1566445,"name":"Sulb Bahrain Al Hidd steel plant","sector":"iron-and-steel","type":"DRI-EAF","lon":50.67954,"lat":26.19937,"emissions":1194207.7},{"id":25451382,"name":"SITRA","sector":"electricity-generation","type":"gas","lon":50.6237,"lat":26.1825,"emissions":724940.0},{"id":32437260,"name":"Askar Cement Plant","sector":"cement","type":"integrated dry","lon":50.59441,"lat":26.03218,"emissions":340383.6},{"id":53059398,"name":"Bahrain_Widyan - North Arabian Gulf_Conventional onshore","sector":"oil-and-gas-transport","type":"","lon":50.55794,"lat":26.03463,"emissions":108634.0}]}